tests/__init__.py
tests/test_is_json.py
tests/test_json_match.py
tests/test_json_schema_match.py
tests/test_match.py
tests/test_rag.py
zeval/__init__.py
zeval/evaluation.py
zeval/config/__init__.py
zeval/config/model_config.py
zeval/evaluators/__init__.py
zeval/evaluators/answer_relevancy.py
zeval/evaluators/context_precision.py
zeval/evaluators/context_recall.py
zeval/evaluators/faithfulness.py
zeval/evaluators/json.py
zeval/evaluators/matchness.py
zeval/utils/__init__.py
zeval/utils/helpers.py
zeval/utils/model.py
zeval/utils/model_caller.py
zeval-0.1.5.dist-info/METADATA
zeval-0.1.5.dist-info/WHEEL
zeval-0.1.5.dist-info/top_level.txt
zeval-0.1.5.dist-info/RECORD
